Metadata-Version: 2.1
Name: nakamoto
Version: 0.1.2.2
Summary: Python Library to Generate Nakamoto Coefficient
Home-page: https://github.com/YazzyYaz/nakamoto-coefficient
Author: Yaz Khoury
Author-email: yaz.khoury@gmail.com
License: MIT
Platform: UNKNOWN
